random_sum_generator/__init__.py
random_sum_generator/core.py
random_sum_generator-0.2.1.dist-info/licenses/LICENSE
random_sum_generator-0.2.1.dist-info/METADATA
random_sum_generator-0.2.1.dist-info/WHEEL
random_sum_generator-0.2.1.dist-info/top_level.txt
random_sum_generator-0.2.1.dist-info/RECORD
