Metadata-Version: 2.4
Name: random_sum_generator
Version: 0.2.1
Summary: Generate random numbers that sum to a total with min/max bounds per part.
Home-page: https://github.com/fahim9778/theBoringCodes/tree/main/RandomSumGenerator
Author: Md. Fakhruddin Gazzali Fahim
Author-email: fahim9778@gmail.com
License: MIT
Project-URL: Bug Tracker, https://github.com/fahim9778/theBoringCodes/issues
Project-URL: Source, https://github.com/fahim9778/theBoringCodes/tree/main/RandomSumGenerator
Classifier: Programming Language :: Python :: 3
Classifier: License :: OSI Approved :: MIT License
Classifier: Operating System :: OS Independent
Classifier: Intended Audience :: Developers
Classifier: Topic :: Software Development :: Libraries
Requires-Python: >=3.6
License-File: LICENSE
Dynamic: author
Dynamic: author-email
Dynamic: classifier
Dynamic: description
Dynamic: description-content-type
Dynamic: home-page
Dynamic: license
Dynamic: license-file
Dynamic: project-url
Dynamic: requires-python
Dynamic: summary
